kivi/Card/Calibration.py
kivi/Card/MasterScale.py
kivi/Card/__init__.py
kivi/Card/card_eval.py
kivi/Card/card_rant.py
kivi/Card/card_score.py
kivi/Card/utils.py
kivi/FeatureTools/FeatureTools.py
kivi/FeatureTools/FeatureToolsV2.py
kivi/FeatureTools/Scale.py
kivi/FeatureTools/__init__.py
kivi/Model/Apriori.py
kivi/Model/Lasso.py
kivi/Model/Linear.py
kivi/Model/LogisticRegression.py
kivi/Model/Ridge.py
kivi/Model/Tree.py
kivi/Model/__init__.py
kivi/Model/simtext.py
kivi/PortfolioAnalysis/PortfolioAnalysis.py
kivi/PortfolioAnalysis/__init__.py
kivi/__init__.py
kivi/ahp/__init__.py
kivi/ahp/ahp.py
kivi/datasets/__init__.py
kivi/datasets/bank.xlsx
kivi/datasets/crime_data.csv
kivi/datasets/dataset.py
kivi/datasets/fake_data.py
kivi/datasets/fake_data_config.py
kivi/datasets/schema.py
kivi/evaluate/BucketsUtils.py
kivi/evaluate/Calibration.py
kivi/evaluate/Heatmap.py
kivi/evaluate/__init__.py
kivi/evaluate/binary_metrics.py
kivi/evaluate/csi.py
kivi/evaluate/model_evaluate.py
kivi/evaluate/psi.py
kivi/evaluate/schema.py
kivi/evaluate/utils.py
kivi/feature/Corr.py
kivi/feature/DefaultAnalysis.py
kivi/feature/VIF.py
kivi/feature/__init__.py
kivi/feature/schema.py
kivi/feature/stepwise.py
kivi/feature/univariate.py
kivi/index/__init__.py
kivi/index/collect.py
kivi/index/datasets.py
kivi/index/date.py
kivi/index/schema.py
kivi/index/utils.py
kivi/sample/__init__.py
kivi/sample/sampling.py
kivi/spark/__init__.py
kivi/spark/column.py
kivi/spark/dataframe.py
kivi/spark/model.py
kivi/spark/operator/__init__.py
kivi/spark/operator/base.py
kivi/spark/operator/operator.py
kivi/spark/operator/pandas_udf.py
kivi/spark/operator/rank.py
kivi/spark/operator/udf.py
kivi/spark/partition.py
kivi/spark/session.py
kivi/spark/table.py
kivi/spark/univariate.py
kivi/sql/SQLengine.py
kivi/sql/__init__.py
kivi/utils/BeautyExcel.py
kivi/utils/__init__.py
kivi/utils/date.py
kivi/utils/encrypt.py
kivi/utils/logger.py
kivi/utils/markdown.py
kivi/utils/operator.py
kivi/utils/utils.py
kivi-0.2.7.dist-info/LICENSE
kivi-0.2.7.dist-info/METADATA
kivi-0.2.7.dist-info/WHEEL
kivi-0.2.7.dist-info/RECORD
