Metadata-Version: 2.1
Name: kivi
Version: 0.2.7
Summary: A LLM Agent Python package.
Home-page: https://kivi-risk.github.io/kivi-doc/
License: MIT
Keywords: llm,agent,embedding,chatbot,prompt
Author: chensy cao
Author-email: chensy.cao@foxmail.com
Requires-Python: >=3.9, !=2.7.*, !=3.0.*, !=3.1.*, !=3.2.*, !=3.3.*, !=3.4.*, !=3.5.*, !=3.6.*, !=3.7.*, !=3.8.*
Classifier: License :: OSI Approved :: MIT License
Classifier: Operating System :: OS Independent
Classifier: Programming Language :: Python :: 3
Classifier: Programming Language :: Python :: 3.9
Classifier: Programming Language :: Python :: 3.10
Classifier: Programming Language :: Python :: 3.11
Classifier: Programming Language :: Python :: 3.12
Classifier: Programming Language :: Python :: 3.8
Classifier: Topic :: Software Development :: Libraries
Classifier: Topic :: Software Development :: Libraries :: Python Modules
Provides-Extra: all
Provides-Extra: jieba
Provides-Extra: pyspark
Provides-Extra: xlsx
Requires-Dist: colorama (>=0.4.6)
Requires-Dist: jieba (>=0.42.1) ; extra == "all" or extra == "jieba"
Requires-Dist: matplotlib (>=3.7.2) ; extra == "all"
Requires-Dist: numpy (>=1.25) ; extra == "all"
Requires-Dist: pandas (>=1.2) ; extra == "all"
Requires-Dist: pydantic (>=2.3)
Requires-Dist: pyspark (>=3.0) ; extra == "all" or extra == "pyspark"
Requires-Dist: scikit-learn (>=1.3.0) ; extra == "all"
Requires-Dist: scipy (>=1.11.2) ; extra == "all"
Requires-Dist: seaborn (>=0.13.0) ; extra == "all"
Requires-Dist: statsmodels (>=0.14.0) ; extra == "all"
Requires-Dist: tqdm (>=4.66.1) ; extra == "all"
Requires-Dist: xlsxwriter (>=3.1.2) ; extra == "all" or extra == "xlsx"
Project-URL: Bug Tracker, https://github.com/kivi-risk/kivi/issues
Project-URL: Repository, https://github.com/kivi-risk/kivi.git
